INTEGRATION.md
LICENSE
MANIFEST.in
README.rst
setup.py
casl/__init__.py
casl/settings.py
casl/urls.py
casl/wsgi.py
casl_django/__init__.py
casl_django/admin.py
casl_django/apps.py
casl_django/config.py
casl_django/manage.py
casl_django/models.py
casl_django/tests.py
casl_django/views.py
casl_django.egg-info/PKG-INFO
casl_django.egg-info/SOURCES.txt
casl_django.egg-info/dependency_links.txt
casl_django.egg-info/top_level.txt
casl_django/casl/__init__.py
casl_django/casl/casl.py
casl_django/casl/converter.py
casl_django/casl/permissions.py
casl_django/casl/utils.py
casl_django/migrations/__init__.py
items/__init__.py
items/admin.py
items/apps.py
items/models.py
items/tests.py
items/views.py
items/migrations/0001_initial.py
items/migrations/__init__.py